projects/__init__.py
projects/pronunciation/__init__.py
projects/pronunciation/pronunciation.py
pyspeedx/__init__.py
pyspeedx/helpers.py
pyspeedx/logger.py
pyspeedx/main.py
pyspeedx/number.py
pyspeedx/search.py
pyspeedx/sort.py
pyspeedx/test.py
pyspeedx/text.py
subp/__init__.py
subp/main.py
subp/test.py
pyspeedx-0.1.1.4.2.8.dist-info/LICENSE.txt
pyspeedx-0.1.1.4.2.8.dist-info/METADATA
pyspeedx-0.1.1.4.2.8.dist-info/WHEEL
pyspeedx-0.1.1.4.2.8.dist-info/top_level.txt
pyspeedx-0.1.1.4.2.8.dist-info/RECORD
